<?xml version="1.0" encoding="UTF-8" ?>
<!DOCTYPE mapper PUBLIC "-//mybatis.org//DTD Mapper 3.0//EN" "http://mybatis.org/dtd/mybatis-3-mapper.dtd" >
<mapper namespace="com.voyageone.security.dao.ComUserTokenDao" >
    <resultMap id="BaseResultMap" type="com.voyageone.security.model.ComUserTokenModel" />
    <sql id="Base_Column_List" >
        `id`, `user_account`, `token`, `created`, `creater`, `modified`, `modifier`
    </sql>

    <select id="select" resultMap="BaseResultMap" parameterType="java.lang.Integer" >
        select 
        <include refid="Base_Column_List" />
        from com_user_token
        where `id` = #{id,jdbcType=INTEGER}
    </select>

    <update id="update" parameterType="com.voyageone.security.model.ComUserTokenModel" >
        update com_user_token
        <set >
            <if test="userAccount != null" >
                `user_account` = #{userAccount,jdbcType=VARCHAR},
            </if>
            <if test="token != null" >
                `token` = #{token,jdbcType=VARCHAR},
            </if>
            <if test="created != null" >
                `created` = #{created,jdbcType=TIMESTAMP},
            </if>
            <if test="creater != null" >
                `creater` = #{creater,jdbcType=VARCHAR},
            </if>
            <if test="modified != null" >
                `modified` = #{modified,jdbcType=TIMESTAMP},
            </if>
            <if test="modified == null" >
                `modified` = now(),
            </if>
            <if test="modifier != null" >
                `modifier` = #{modifier,jdbcType=VARCHAR},
            </if>
        </set>
        where `id` = #{id,jdbcType=INTEGER}
    </update>

    <delete id="delete" parameterType="java.lang.Integer" >
        delete from com_user_token
        where `id` = #{id,jdbcType=INTEGER}
    </delete>

    <select id="selectOne" resultMap="BaseResultMap" >
        select 
        <include refid="Base_Column_List" />
        from com_user_token
        <where >
            <if test="userAccount != null" >
                and `user_account` = #{userAccount,jdbcType=VARCHAR}
            </if>
            <if test="token != null" >
                and `token` = #{token,jdbcType=VARCHAR}
            </if>
            <if test="created != null" >
                and `created` = #{created,jdbcType=TIMESTAMP}
            </if>
            <if test="creater != null" >
                and `creater` = #{creater,jdbcType=VARCHAR}
            </if>
            <if test="modified != null" >
                and `modified` = #{modified,jdbcType=TIMESTAMP}
            </if>
            <if test="modifier != null" >
                and `modifier` = #{modifier,jdbcType=VARCHAR}
            </if>
        </where>
        limit 1
    </select>

    <select id="selectList" resultMap="BaseResultMap" >
        select 
        <include refid="Base_Column_List" />
        from com_user_token
        <where >
            <if test="userAccount != null" >
                and `user_account` = #{userAccount,jdbcType=VARCHAR}
            </if>
            <if test="token != null" >
                and `token` = #{token,jdbcType=VARCHAR}
            </if>
            <if test="created != null" >
                and `created` = #{created,jdbcType=TIMESTAMP}
            </if>
            <if test="creater != null" >
                and `creater` = #{creater,jdbcType=VARCHAR}
            </if>
            <if test="modified != null" >
                and `modified` = #{modified,jdbcType=TIMESTAMP}
            </if>
            <if test="modifier != null" >
                and `modifier` = #{modifier,jdbcType=VARCHAR}
            </if>
        </where>
    </select>

    <select id="selectCount" resultType="java.lang.Integer" >
        select count(*) from com_user_token
        <where >
            <if test="userAccount != null" >
                and `user_account` = #{userAccount,jdbcType=VARCHAR}
            </if>
            <if test="token != null" >
                and `token` = #{token,jdbcType=VARCHAR}
            </if>
            <if test="created != null" >
                and `created` = #{created,jdbcType=TIMESTAMP}
            </if>
            <if test="creater != null" >
                and `creater` = #{creater,jdbcType=VARCHAR}
            </if>
            <if test="modified != null" >
                and `modified` = #{modified,jdbcType=TIMESTAMP}
            </if>
            <if test="modifier != null" >
                and `modifier` = #{modifier,jdbcType=VARCHAR}
            </if>
        </where>
    </select>

    <insert id="insert" parameterType="com.voyageone.security.model.ComUserTokenModel" useGeneratedKeys="true" keyProperty="id" >
        insert into com_user_token
        <trim prefix="(" suffix=")" suffixOverrides="," >
            <if test="userAccount != null" >
                `user_account`,
            </if>
            <if test="token != null" >
                `token`,
            </if>
            `created`,
            <if test="creater != null" >
                `creater`,
            </if>
            `modified`,
            <if test="modifier != null" >
                `modifier`,
            </if>
            <if test="modifier == null and creater != null" >
                `modifier`,
            </if>
        </trim>
        <trim prefix="values (" suffix=")" suffixOverrides="," >
            <if test="userAccount != null" >
                #{userAccount,jdbcType=VARCHAR},
            </if>
            <if test="token != null" >
                #{token,jdbcType=VARCHAR},
            </if>
            <if test="created == null" >
                now(),
            </if>
            <if test="created != null" >
                #{created,jdbcType=TIMESTAMP},
            </if>
            <if test="creater != null" >
                #{creater,jdbcType=VARCHAR},
            </if>
            <if test="modified == null" >
                now(),
            </if>
            <if test="modified != null" >
                #{modified,jdbcType=TIMESTAMP},
            </if>
            <if test="modifier != null" >
                #{modifier,jdbcType=VARCHAR},
            </if>
            <if test="modifier == null and creater != null" >
                #{creater,jdbcType=VARCHAR},
            </if>
        </trim>
    </insert>

</mapper>